{
  "date": "2025-09-30",
  "categories": [
    {
      "title": "UNNATURAL, AS MANNERISMS",
      "words": [
        "AWKWARD",
        "STIFF",
        "STILTED",
        "WOODEN"
      ]
    },
    {
      "title": "WORDS IN A FAMOUS TONGUE TWISTER",
      "words": [
        "CHUCK",
        "COULD",
        "WOOD",
        "WOODCHUCK"
      ]
    },
    {
      "title": "CARTOON BIRDS",
      "words": [
        "FOGHORN",
        "SCROOGE",
        "WOODSTOCK",
        "WOODY"
      ]
    },
    {
      "title": "ENDING WITH NUMBER HOMOPHONES",
      "words": [
        "CAMPHOR",
        "CLASSICS",
        "CREATE",
        "GUTHRIE"
      ]
    }
  ]
}