{
  "date": "2025-12-04",
  "categories": [
    {
      "title": "LAY IT ON THICK",
      "words": [
        "FAWN",
        "FLATTER",
        "GUSH",
        "PRAISE"
      ]
    },
    {
      "title": "HANS CHRISTIAN ANDERSON FIGURES",
      "words": [
        "DUCKLING",
        "EMPEROR",
        "MERMAID",
        "PRINCESS"
      ]
    },
    {
      "title": "SILENT L",
      "words": [
        "CALF",
        "CHALK",
        "COLONEL",
        "WOULD"
      ]
    },
    {
      "title": "FICTIONAL PIGS",
      "words": [
        "BABE",
        "NAPOLEON",
        "PIGLET",
        "PORKY"
      ]
    }
  ]
}