{
  "date": "2026-05-16",
  "categories": [
    {
      "title": "CONTRACT",
      "words": [
        "AGREEMENT",
        "BARGAIN",
        "DEAL",
        "UNDERSTANDING"
      ]
    },
    {
      "title": "EDIT MENU OPTIONS",
      "words": [
        "COPY",
        "CUT",
        "DELETE",
        "PASTE"
      ]
    },
    {
      "title": "KINDS OF BASKETS",
      "words": [
        "EASTER",
        "GROCERY",
        "LAUNDRY",
        "PICNIC"
      ]
    },
    {
      "title": "SYMBOLIZED WITH ARROWS",
      "words": [
        "RECYCLING",
        "SHUFFLE",
        "THISSIDEUP",
        "U-TURN"
      ]
    }
  ]
}